{
  "dates": [
    {
      "date": "2021-01-21",
      "message": "come here now",
      "id": 10
    },
    {
      "date": "2021-01-21",
      "message": "back to home today",
      "id": 11
    },
    {
      "date": "2021-01-11",
      "message": "come here now",
      "id": 12
    },
    {
      "date": "2021-01-07",
      "message": "come here now",
      "id": 17
    },
    {
      "date": "2021-06-10",
      "message": "formation Wild code school",
      "id": 18
    },
    {
      "date": "2021-01-15",
      "message": "On pourrait vous dire que vous avez besoin de changement, de réconfort, de bons petits plats livrés rapidement chez vous.",
      "id": 19
    }
  ],
  "galleries": [
    {
      "id": 1,
      "title": "stage Kiabi",
      "date": "2021-01-21",
      "text": "nice stage",
      "images": [
        "https://www.pagesjaunes.fr/media/ugc/kiabi_08938700_104056745",
        "https://www.qwartz-92.com/-/media/qwartz92/images/header/kiabi.ashx"
      ]
    },
    {
      "title": "Wilder in Lille",
      "date": "2021-01-11",
      "text": "stage at wild code school",
      "images": [
        "https://i.ibb.co/ydx5f6B/ABT5-D0-BF1-B26328-B0-A3991-FC22-FC0-AC2912-DE1-A6-BD9-FF1-EF81-E47121-C652042-B667.jpg"
      ],
      "id": 2
    }
  ]
}